.gitignore
LICENSE
README.md
requirements.txt
easyrsa/__init__.py
easyrsa/core.py
easyrsa/utils.py
easyrsa/__metadata__/LICENSE
easyrsa/__metadata__/README.md
easyrsa/__metadata__/__init__.py
easyrsa/__metadata__/requirements.txt
easyrsa-3.0.0.dist-info/METADATA
easyrsa-3.0.0.dist-info/WHEEL
easyrsa-3.0.0.dist-info/top_level.txt
easyrsa-3.0.0.dist-info/RECORD
